{
  "landingPages": [
    {
      "id": 1,
      "title": "School Dashboard",
      "link": "https://school-dashboard404.netlify.app/",
      "img":"https://codelover404.github.io/jsonapi/website/img1.png",
      "type":"landingPage"
    },
    {
      "id": 2,
      "title": "NFT Showcase",
      "link": "https://nft-site-demo.netlify.app",
      "img":"https://codelover404.github.io/jsonapi/website/img6.png",
      "type":"landingPage"
    },
     {
      "id": 2,
      "title": "NFT Showcase",
      "link": "https://nft-site-demo.netlify.app",
      "img":"https://codelover404.github.io/jsonapi/website/img4.png",
      "type":"landingPage"
     },
     {
      "id": 2,
      "title": "NFT Showcase",
      "link": "https://nft-site-demo.netlify.app",
      "img":"https://codelover404.github.io/jsonapi/website/img3.png",
      "type":"landingPage"
    }
  ]
  
}
